clamor/__init__.py
clamor/meta.py
tests/__init__.py
clamor-0.1.0.dist-info/LICENSE
clamor-0.1.0.dist-info/METADATA
clamor-0.1.0.dist-info/WHEEL
clamor-0.1.0.dist-info/top_level.txt
clamor-0.1.0.dist-info/RECORD
