Metadata-Version: 2.1
Name: clamor
Version: 0.1.0
Summary: The Python Discord API Framework
Home-page: https://github.com/clamor-py/Clamor
Author: Valentin B.
Author-email: valentin.be@protonmail.com
License: MIT
Project-URL: Documentation, https://clamor.readthedocs.io/en/latest
Project-URL: Source, https://github.com/clamor-py/Clamor
Project-URL: Issue tracker, https://github.com/clamor-py/Clamor/issues
Keywords: discord discord-api rest-api api wrapper websocket api-client library framework
Platform: UNKNOWN
Classifier: Development Status :: 4 - Beta
Classifier: License :: OSI Approved :: MIT License
Classifier: Intended Audience :: Developers
Classifier: Natural Language :: English
Classifier: Operating System :: OS Independent
Classifier: Programming Language :: Python :: 3.5
Classifier: Programming Language :: Python :: 3.6
Classifier: Programming Language :: Python :: 3.7
Classifier: Programming Language :: Python :: Implementation :: CPython
Classifier: Topic :: Software Development :: Libraries
Classifier: Topic :: Software Development :: Libraries :: Application Frameworks
Classifier: Topic :: Software Development :: Libraries :: Python Modules
Classifier: Topic :: Utilities
Requires-Python: >=3.5.0
Requires-Dist: anyio (==1.0.0)
Requires-Dist: asks (>=2.3.5)
Requires-Dist: anysocks (>=0.1.2)
